audiospylt/__init__.py
audiospylt/audio_utils.py
audiospylt/dft_analysis.py
audiospylt/generate_wave_file.py
audiospylt/io_utils.py
audiospylt/mei.py
audiospylt/mei_old.py
audiospylt/multiplotter.py
audiospylt/plot_wave.py
audiospylt/plotting.py
audiospylt/waveform_utils.py
audiospylt-0.6.0a0.dist-info/licenses/LICENSE
audiospylt-0.6.0a0.dist-info/METADATA
audiospylt-0.6.0a0.dist-info/WHEEL
audiospylt-0.6.0a0.dist-info/top_level.txt
audiospylt-0.6.0a0.dist-info/RECORD
