Metadata-Version: 2.4
Name: audiospylt
Version: 0.6.0a0
Summary: Python toolbox for sound analysis, resynthesis, and visual/symbolic representations.
Author: egorpol
License: MIT License
Project-URL: Changelog, https://github.com/egorpol/audiospylt/blob/main/CHANGELOG.md
Project-URL: Repository, https://github.com/egorpol/audiospylt
Keywords: audio,dft,resynthesis,music,mei,visualization
Classifier: Development Status :: 3 - Alpha
Classifier: Intended Audience :: Education
Classifier: License :: OSI Approved :: MIT License
Classifier: Programming Language :: Python :: 3
Classifier: Programming Language :: Python :: 3 :: Only
Classifier: Programming Language :: Python :: 3.10
Classifier: Programming Language :: Python :: 3.11
Classifier: Programming Language :: Python :: 3.12
Requires-Python: >=3.10
License-File: LICENSE
Requires-Dist: ipython
Requires-Dist: ipywidgets
Requires-Dist: librosa
Requires-Dist: matplotlib
Requires-Dist: nbformat>=4.2.0
Requires-Dist: numpy
Requires-Dist: pandas
Requires-Dist: plotly
Requires-Dist: requests
Requires-Dist: scipy
Requires-Dist: soundfile
Requires-Dist: tqdm
Requires-Dist: verovio
Provides-Extra: dev
Requires-Dist: build; extra == "dev"
Requires-Dist: pytest; extra == "dev"
Requires-Dist: ruff; extra == "dev"
Requires-Dist: twine; extra == "dev"
Dynamic: license-file
